{
  "id": 13727,
  "name": "Butterfly",
  "mask": "           7                  77                 7777               77377              3335377            333 1537           333 11153 1         333 15153 1 1 7     3333 153 1 1 77   77 333 553 11 777  777733333331113557  733773333311333513   3557333311333353   3315373 11 33333  33335533311377       33333333113377       33333 1135577            11 3513               3333               333         ",
  "width": 20,
  "height": 20,
  "palette": {
    "1": "000000",
    "3": "f68e54",
    "5": "fff100",
    "7": "9d0a0f"
  },
  "player_mask": null,
  "completed": false
}
