{
  "id": 14391,
  "name": "Corella parrot",
  "mask": "        5        55       555       555      5555      5        3  1 5    3 4  5   33   7   332       322   2  332    22 33      2 332     2 322     2 32     22  2     2 6666161666  3333      333      333       333       33        3         3        ",
  "width": 10,
  "height": 25,
  "palette": {
    "1": "000000",
    "2": "adad85",
    "3": "6b6b47",
    "4": "ff9966",
    "5": "ffcc00",
    "6": "cc3300",
    "7": "ff6600"
  },
  "player_mask": null,
  "completed": false
}
