{
  "id": 14675,
  "mask": "           4444                4   44              24 2  44            224    34          2222243  34                43 34                 4 34                 4 34              5114 34    4         5511 34 11144        5551 34111543444444445551 311555433333333355515515555 43        5551155555 43 4        5115555  43 433     5555555   43 443     551 5155  43  4333   151 4155  433  443333311 41555 443    44444   41155  433         334 11    433       334         43333333334           433333444             44444                 2  2                 2  22                22  222               222          ",
  "width": 21,
  "height": 29,
  "palette": {
    "1": "d46591",
    "2": "d17e5c",
    "3": "ebd8b4",
    "4": "dbb569",
    "5": "cc145a"
  },
  "player_mask": null,
  "completed": false
}
