{
  "id": 14688,
  "name": "Duck",
  "mask": "              22222 33                  22   2333                 222   233                  222 1 233                  222 1 23                   2222 22                     222222                    222221                    666222          11111     111662           1111111  611116            661111112111111             661111211111111111           111211111111111111         61211111111111111111       611111111111111111111       111111111111111111111      11111111116661111161111   11111111166  66616166666  1111111116     666666       616111166                   6666666                     66666                      16 61                     33  63                    333  33                    333 333                     3  333                         3                  ",
  "width": 27,
  "height": 29,
  "palette": {
    "1": "0c0e0c",
    "2": "045f20",
    "3": "f7941d",
    "6": "c4c6cc"
  },
  "player_mask": null,
  "completed": false
}
