{
  "id": 15897,
  "mask": "                                       3                                            3                      1111                334          33        115511             33334           333     11 1 51            333344      2    43333    155511           3333344      22   44 333   11111111         333 444       2   444 33    11311111        33 444        22   44 333  1113311111      33 4444        222  444 33  1615331111      3 4444          2222 44 33  16115331111     3444            2 222 4 33  166115533333   22              2   222 43    66611155555 222                    222 4    666655111111                        6222     6666655555555                  4444463222  1166661311                     4444  3 2622122 16661311             2    444   333  262222 1    1355      22  22 4  444  3333    46662221    1355   222 222   4443333333     43  66622222513552222222       3333333     4 43    6226665135566666222                44 43      22  351355      22               444 43      62  351355       2              444 43      62   3                          444 43      2    3                          44 433                                      44 433                                       4433                                         43                                          33                                         33                           ",
  "width": 44,
  "height": 31,
  "palette": {
    "1": "000000",
    "2": "7b3000",
    "3": "8fc63d",
    "4": "588528",
    "5": "5e5ca7",
    "6": "f7941d"
  },
  "player_mask": null,
  "completed": false
}
