{
  "id": 15901,
  "name": "Cat",
  "mask": "               333     3     3     3443   343   323     3443  343333223      343  3444   23      3 3 34444 2   3    32 3 3414 212 233333223 3344 1 2  23444223   322333  22344423   3 322   223 444 3      3333333  44  3        33         3        323  3333323        32323  32323         3323  33223          33    333    ",
  "width": 20,
  "height": 16,
  "palette": {
    "1": "000000",
    "2": "fdc68c",
    "3": "8c0214",
    "4": "fc7e24"
  },
  "player_mask": null,
  "completed": false
}
