{
  "id": 16651,
  "mask": "                         1                                             111                                             1                                            11211                                         1111211                                        1111211                                          55                                             5                                              5 5                                            5 5                                           11111                                       11111122111                                    11111132111                                    11111132111                                    11111112111                                    11111122111                                     333333333                                       3333333                                        1112221                                        1112221                                        1143341                                        1133331                                        1143341                                        3333333                                       444555544                                      444455544                                      445555554                                      445344354                                      445433454                                      455333354                                      455433454                                      333333333                            666   6  44445555554                        6666  6   6 44444545554                       6666 66666 6 44455555544                        66 6666666 644444555554                    66 76  7  66 66646555555554                 6   67   7677766 66644455555454                 66  7  767   766 6445533335554               66  6  7 77    676 6645543345554               6 666   776 777 76 6644533335544                 6666       6767664655543345554333             666666     65677664645533335554  333          6 667666 7  65676654444543345544    333            6766  76656665666             33433            6676  7655676666566       333334433     6      6676  75667766653566333333333334433    66     6676 67666776765333463333334443334333  6      6666 676667746665333335333434443334333 66      6663366664746667533335644444444333443336 6666  763333 6644466755633356643335444434533366666 777777  7744446475465356664545334443565336666        77   4 77 44464466766555333343366336667      777777 777 44446666677665633334336666677      77  777 77     6666777665555333337766677                   66666677677566733  7777777                  666 667776666 7777                               6666666       667777                           66          777777               ",
  "width": 47,
  "height": 59,
  "palette": {
    "1": "92000a",
    "2": "f16c4d",
    "3": "4d2d00",
    "4": "959595",
    "5": "fdc68c",
    "6": "ace5ee",
    "7": "16bcb4"
  },
  "player_mask": null,
  "completed": false
}
