{
  "id": 16717,
  "name": "Carnation",
  "mask": "       33 33          333 313        3333311333      1131311333 2     11131133  42    444413313342   2444331333 442  22222111333 44 222221331133  4 222 3313311    2    33113      2      31       2              2 4444          2442224        2222   22       2               2               2              ",
  "width": 16,
  "height": 19,
  "palette": {
    "1": "940204",
    "2": "14a214",
    "3": "d40204",
    "4": "045f20"
  },
  "player_mask": null,
  "completed": false
}
