{
  "id": 18113,
  "name": "funny carrot",
  "mask": "                   1111111                     11777766711                  1777766776671                177776777776671              1677777777766661          11112267777776666621         18832222222266666621         18333331111122222111         18333333881  11111            183333333881                 1833383888881                 133333333881                 181331388881              11  18133133881              1381 18     881               1881 18     881               14111138   88141               1488483888888141               111183388881141                   1888881381                    1888881881                   1418888111                   131 188141                   131   188141                  131    11141                  141       141                 1141      14111              13841       14831            138881       188831          ",
  "width": 30,
  "height": 29,
  "palette": {
    "1": "000000",
    "2": "3c8674",
    "3": "fcb214",
    "4": "ac2a0c",
    "6": "5cc674",
    "7": "bce634",
    "8": "ec421c"
  },
  "player_mask": null,
  "completed": false
}
