{
  "id": 18448,
  "name": "Lily of the valley",
  "mask": "             111                 111111              55    111       33333555     11      34444425      51     344    43      11    344     43      11    333332  43     51       3 23  43     11       34 3 443     11       3333443     51    11     343      11  1111     33       11 1111         1     111111          11    11111           151   1111            1551 1111             115111111              1511111               1551111                15511                 15511                 11511                  151                   111                    11        ",
  "width": 22,
  "height": 26,
  "palette": {
    "1": "0cae2c",
    "2": "fcf204",
    "3": "7ceefc",
    "4": "c4f6fc",
    "5": "04d214"
  },
  "player_mask": null,
  "completed": false
}
