{
  "id": 5187,
  "name": "Fox cub",
  "mask": "  3           3          33 34444   333         33334  23 3333          3322222233333         3322224422233          441222 112223          411222 112223        112222444444433         44444444    4           4   43   444            4   44444               444  43                   4443                  4   23                 4   2233              4    22223             4   22322233            4 22322222333          4 2333333332333        3233     3222233      3233   22222222223   332234  222222222233     3334   2222222233       444443322222333              3333333    ",
  "width": 23,
  "height": 25,
  "palette": {
    "1": "000000",
    "2": "f4961c",
    "3": "f46624",
    "4": "b4b6b4"
  },
  "player_mask": null,
  "completed": false
}
