{
  "id": 9747,
  "name": "Slobbering friend",
  "mask": "    777              12271777            2 2277777           47 22477777         777  5 7774711227727777     777411727172117    3  24777222222117        2222222271777         227222777777           22       7   333    2        7   ",
  "width": 21,
  "height": 11,
  "palette": {
    "1": "000000",
    "2": "c4c2c4",
    "3": "9cdaec",
    "4": "8c0214",
    "5": "fcaecc",
    "7": "bc7a54"
  },
  "player_mask": null,
  "completed": false
}
